hatch_vcs_tunable/__init__.py
hatch_vcs_tunable/_version.py
hatch_vcs_tunable/build_hook.py
hatch_vcs_tunable/const.py
hatch_vcs_tunable/hooks.py
hatch_vcs_tunable/metadata_hook.py
hatch_vcs_tunable/py.typed
hatch_vcs_tunable/version_source.py
hatch_vcs_tunable-0.0.1a3.dist-info/METADATA
hatch_vcs_tunable-0.0.1a3.dist-info/WHEEL
hatch_vcs_tunable-0.0.1a3.dist-info/entry_points.txt
hatch_vcs_tunable-0.0.1a3.dist-info/licenses/LICENSE
hatch_vcs_tunable-0.0.1a3.dist-info/RECORD
