Metadata-Version: 2.4
Name: hatch-vcs-tunable
Version: 0.0.1a3
Summary: Define your package's version from vcs refs, with build-time tuning of which tags to use.
Project-URL: Documentation, https://github.com/Opentrons/hatch-plugins/tree/main/hatch-vcs-tunable#readme
Project-URL: Issues, https://github.com/Opentrons/hatch-plugins/issues
Project-URL: Source, https://github.com/Opentrons/hatch-plugins/tree/main/hatch-vcs-tunable
Project-URL: Changelog, https://github.com/Opentrons/hatch-plugins/tree/main/hatch-vcs-tunable/CHANGES.md
Author-email: Opentrons Engineering <engineering@opentrons.com>
License-Expression: Apache-2.0
License-File: LICENSE
Keywords: git,hatch,mercurial,plugin,version
Classifier: Development Status :: 4 - Beta
Classifier: Framework :: Hatch
Classifier: Programming Language :: Python
Classifier: Programming Language :: Python :: 3.8
Classifier: Programming Language :: Python :: 3.9
Classifier: Programming Language :: Python :: 3.10
Classifier: Programming Language :: Python :: 3.11
Classifier: Programming Language :: Python :: 3.12
Classifier: Programming Language :: Python :: Implementation :: CPython
Classifier: Programming Language :: Python :: Implementation :: PyPy
Requires-Python: >=3.8
Requires-Dist: hatch-vcs<1.0.0,>=0.3.0
